mergeplg/__init__.py
mergeplg/base.py
mergeplg/bk_functions.py
mergeplg/example_data/openmrg_cml.nc
mergeplg/example_data/openmrg_municp_gauge.nc
mergeplg/example_data/openmrg_rad.nc
mergeplg/example_data/openmrg_smhi_gauge.nc
mergeplg/interpolate.py
mergeplg/io.py
mergeplg/merge.py
mergeplg/py.typed
mergeplg/radolan/__init__.py
mergeplg/radolan/adjust.py
mergeplg/radolan/check_data_struct.py
mergeplg/radolan/idw.py
mergeplg/radolan/io.py
mergeplg/radolan/processing.py
mergeplg-0.1.0.dist-info/LICENSE
mergeplg-0.1.0.dist-info/METADATA
mergeplg-0.1.0.dist-info/WHEEL
mergeplg-0.1.0.dist-info/RECORD
