Metadata-Version: 2.3
Name: mergeplg
Version: 0.1.0
Summary: A great package.
License: BSD-3-Clause
Author: Christian Chwala
Author-email: christian.chwala@kit.edu
Requires-Python: >=3.10,<4.0.0
Classifier: Development Status :: 1 - Planning
Classifier: Intended Audience :: Developers
Classifier: Intended Audience :: Science/Research
Classifier: License :: OSI Approved :: BSD License
Classifier: Operating System :: OS Independent
Classifier: Programming Language :: Python :: 3
Classifier: Programming Language :: Python :: 3.10
Classifier: Programming Language :: Python :: 3.11
Classifier: Programming Language :: Python :: 3.12
Classifier: Programming Language :: Python :: 3.13
Classifier: Topic :: Scientific/Engineering
Classifier: Typing :: Typed
Provides-Extra: dev
Provides-Extra: docs
Provides-Extra: test
Requires-Dist: docutils (!=0.21.post1) ; extra == "docs"
Requires-Dist: furo (>=2023.08.17) ; extra == "docs"
Requires-Dist: ipython ; extra == "docs"
Requires-Dist: myst_parser (>=0.13) ; extra == "docs"
Requires-Dist: nbmake (>=1.4.6) ; extra == "test" or extra == "dev"
Requires-Dist: nbsphinx ; extra == "docs"
Requires-Dist: numba
Requires-Dist: numpy (>=2.0.1)
Requires-Dist: pandas (>=2.2.2)
Requires-Dist: poligrain (>=0.3.0)
Requires-Dist: pykrige (>=1.7.2)
Requires-Dist: pytest (>=6) ; extra == "test" or extra == "dev"
Requires-Dist: pytest-cov (>=3) ; extra == "test" or extra == "dev"
Requires-Dist: scikit-gstat (>=1.0.17)
Requires-Dist: scikit-learn (>=1.5.1)
Requires-Dist: scipy (>=1.14.0)
Requires-Dist: sphinx (>=7.0) ; extra == "docs"
Requires-Dist: sphinx-autodoc-typehints ; extra == "docs"
Requires-Dist: sphinx_copybutton (>=0.3.0) ; extra == "docs"
Requires-Dist: wradlib (>=2.0.3)
Requires-Dist: xarray (>=2024.6.0,<2024.9.0)
Requires-Dist: xarray-datatree (<=0.0.14)
Project-URL: Homepage, https://github.com/OpenSenseAction/mergeplg
Project-URL: Repository, https://github.com/OpenSenseAction/mergeplg
